LICENSE
MANIFEST.in
README.md
requirements.txt
setup.py
src/djangosaml2_spid/__init__.py
src/djangosaml2_spid/_saml2.py
src/djangosaml2_spid/apps.py
src/djangosaml2_spid/conf.py
src/djangosaml2_spid/spid_attributes.py
src/djangosaml2_spid/spid_errors.py
src/djangosaml2_spid/spid_metadata.py
src/djangosaml2_spid/spid_request.py
src/djangosaml2_spid/spid_validator.py
src/djangosaml2_spid/tests.py
src/djangosaml2_spid/urls.py
src/djangosaml2_spid/utils.py
src/djangosaml2_spid/views.py
src/djangosaml2_spid.egg-info/PKG-INFO
src/djangosaml2_spid.egg-info/SOURCES.txt
src/djangosaml2_spid.egg-info/dependency_links.txt
src/djangosaml2_spid.egg-info/not-zip-safe
src/djangosaml2_spid.egg-info/requires.txt
src/djangosaml2_spid.egg-info/top_level.txt
src/djangosaml2_spid/attribute_maps/__init__.py
src/djangosaml2_spid/attribute_maps/satosa_spid_basic_hybrid.py
src/djangosaml2_spid/attribute_maps/satosa_spid_uri_hybrid.py
src/djangosaml2_spid/management/__init__.py
src/djangosaml2_spid/management/commands/__init__.py
src/djangosaml2_spid/management/commands/update_idps.py
src/djangosaml2_spid/migrations/__init__.py
src/djangosaml2_spid/static/spid/bootstrap-italia.css
src/djangosaml2_spid/static/spid/bootstrap-italia.js
src/djangosaml2_spid/static/spid/bootstrap-italia.min.css.map
src/djangosaml2_spid/static/spid/brython.js
src/djangosaml2_spid/static/spid/logo.jpg
src/djangosaml2_spid/static/spid/logo_white.png
src/djangosaml2_spid/static/spid/spid-ico-circle-bb.svg
src/djangosaml2_spid/static/spid/spid-idp-arubaid.svg
src/djangosaml2_spid/static/spid/spid-idp-infocertid.svg
src/djangosaml2_spid/static/spid/spid-idp-intesaid.svg
src/djangosaml2_spid/static/spid/spid-idp-lepidaid.svg
src/djangosaml2_spid/static/spid/spid-idp-namirialid.svg
src/djangosaml2_spid/static/spid/spid-idp-posteid.svg
src/djangosaml2_spid/static/spid/spid-idp-sielteid.svg
src/djangosaml2_spid/static/spid/spid-idp-spiditalia.svg
src/djangosaml2_spid/static/spid/spid-idp-timid.svg
src/djangosaml2_spid/static/spid/spid-sp-access-button.css
src/djangosaml2_spid/static/spid/spid-sp-access-button.js
src/djangosaml2_spid/static/spid/spid_button.js
src/djangosaml2_spid/static/spid/sprite.svg
src/djangosaml2_spid/static/spid/fonts/Lora/Lora-Bold.ttf
