Metadata-Version: 2.1
Name: djangosaml2-spid
Version: 1.1.4
Summary: Djangosaml2 SPID Service Provider
Home-page: https://github.com/italia/djangosaml2_spid
Author: Giuseppe De Marco
Author-email: demarcog83@gmail.com
License: Apache 2.0
Platform: UNKNOWN
Classifier: Development Status :: 5 - Production/Stable
Classifier: License :: OSI Approved :: Apache Software License
Classifier: Programming Language :: Python :: 3.6
Classifier: Programming Language :: Python :: 3.7
Classifier: Programming Language :: Python :: 3.8
Classifier: Programming Language :: Python :: 3.9
Classifier: Programming Language :: Python :: Implementation :: CPython
Classifier: Topic :: Software Development :: Libraries :: Python Modules
